{
  "title": "VIM MOMENT FEMALE EVENT",
  "thumbnail": "/images/uploads/photo_2025-11-29_17-56-27.jpg",
  "date": "2025-11-29T21:06:00.000+03:00",
  "body": "![](/images/uploads/photo_2025-11-29_17-56-27.jpg \"VIM MOMENT EVENT Teamlist\")\n\nНаши прекрасные дамы уже запустились на первую карту   \n\n« VIM MOMENT EVENT »\n\nС призовым фондом 15.000₽.\n\nМы приглашаем вас присоединиться к трансляции этого мероприятия! Заходите на стрим и поддерживайте свои любимые коллективы \n\nSTREAM: [YouTube](https://www.youtube.com/watch?v=G8mFARMFjxo) || [Twitch](https://www.twitch.tv/ronin_caster)\n\n\\#VINCEREMORTEM #PUBGMobile",
  "category": "PUBG TOURNAMENTS"
}
